{
  "aspectWidth": 4,
  "aspectHeight": 3,
  "enableKeyboardZoom": true,
  "enableKeyboardRotation": true,
  "enableKeyboardNavigation": true,
  "enableMouseTranslation": true,
  "enableMouseZoom": true,
  "enableMouseRotation": true,
  "enableMouseNavigation": true,
  "updateURLOnFrameChange": true,
  "frames": [
    {
      "frameId": "frame7041",
      "title": "New frame",
      "titleLevel": 0,
      "notes": "",
      "timeoutMs": 0,
      "timeoutEnable": false,
      "transitionDurationMs": 1000,
      "showInFrameList": true,
      "showFrameNumber": true,
      "layerProperties": {
        "layer1": {
          "link": false,
          "referenceElementId": "",
          "outlineElementId": "",
          "transitionTimingFunction": "linear",
          "transitionRelativeZoom": 0,
          "transitionPathId": ""
        },
        "__sozi_auto__": {
          "link": false,
          "referenceElementId": "",
          "outlineElementId": "",
          "transitionTimingFunction": "linear",
          "transitionRelativeZoom": 0,
          "transitionPathId": ""
        }
      },
      "cameraStates": {
        "layer1": {
          "cx": 133.59833024587587,
          "cy": 106.09000922296092,
          "width": 283.8040999914927,
          "height": 213.08418582423147,
          "opacity": 1,
          "angle": 0,
          "clipped": true,
          "clipXOffset": 0,
          "clipYOffset": 0,
          "clipWidthFactor": 0.9999999999999989,
          "clipHeightFactor": 0.9999999999999993
        },
        "__sozi_auto__": {
          "cx": 133.59833024587587,
          "cy": 106.09000922296092,
          "width": 283.8040999914927,
          "height": 213.08418582423147,
          "opacity": 1,
          "angle": 0,
          "clipped": true,
          "clipXOffset": 0,
          "clipYOffset": 0,
          "clipWidthFactor": 0.9999999999999989,
          "clipHeightFactor": 0.9999999999999993
        }
      },
      "cameraOffsets": {}
    },
    {
      "frameId": "frame6653",
      "title": "New frame",
      "titleLevel": 0,
      "notes": "",
      "timeoutMs": 0,
      "timeoutEnable": false,
      "transitionDurationMs": 1000,
      "showInFrameList": true,
      "showFrameNumber": true,
      "layerProperties": {
        "layer1": {
          "link": false,
          "referenceElementId": "",
          "outlineElementId": "",
          "transitionTimingFunction": "linear",
          "transitionRelativeZoom": 0,
          "transitionPathId": ""
        },
        "__sozi_auto__": {
          "link": false,
          "referenceElementId": "",
          "outlineElementId": "",
          "transitionTimingFunction": "linear",
          "transitionRelativeZoom": 0,
          "transitionPathId": ""
        }
      },
      "cameraStates": {
        "layer1": {
          "cx": 133.13610858465196,
          "cy": 301.147550259459,
          "width": 283.8040999914927,
          "height": 213.08418582423147,
          "opacity": 1,
          "angle": 0,
          "clipped": true,
          "clipXOffset": 0,
          "clipYOffset": 0,
          "clipWidthFactor": 0.9999999999999989,
          "clipHeightFactor": 0.9999999999999993
        },
        "__sozi_auto__": {
          "cx": 133.13610858465196,
          "cy": 301.147550259459,
          "width": 283.8040999914927,
          "height": 213.08418582423147,
          "opacity": 1,
          "angle": 0,
          "clipped": true,
          "clipXOffset": 0,
          "clipYOffset": 0,
          "clipWidthFactor": 0.9999999999999989,
          "clipHeightFactor": 0.9999999999999993
        }
      },
      "cameraOffsets": {}
    },
    {
      "frameId": "frame3269",
      "title": "New frame",
      "titleLevel": 0,
      "notes": "",
      "timeoutMs": 0,
      "timeoutEnable": false,
      "transitionDurationMs": 1000,
      "showInFrameList": true,
      "showFrameNumber": true,
      "layerProperties": {
        "layer1": {
          "link": false,
          "referenceElementId": "",
          "outlineElementId": "",
          "transitionTimingFunction": "linear",
          "transitionRelativeZoom": 0,
          "transitionPathId": ""
        },
        "__sozi_auto__": {
          "link": false,
          "referenceElementId": "",
          "outlineElementId": "",
          "transitionTimingFunction": "linear",
          "transitionRelativeZoom": 0,
          "transitionPathId": ""
        }
      },
      "cameraStates": {
        "layer1": {
          "cx": 134.5227735683237,
          "cy": 497.12953461840567,
          "width": 283.8040999914927,
          "height": 213.08418582423147,
          "opacity": 1,
          "angle": 0,
          "clipped": true,
          "clipXOffset": 0,
          "clipYOffset": 0,
          "clipWidthFactor": 0.9999999999999989,
          "clipHeightFactor": 0.9999999999999993
        },
        "__sozi_auto__": {
          "cx": 134.5227735683237,
          "cy": 497.12953461840567,
          "width": 283.8040999914927,
          "height": 213.08418582423147,
          "opacity": 1,
          "angle": 0,
          "clipped": true,
          "clipXOffset": 0,
          "clipYOffset": 0,
          "clipWidthFactor": 0.9999999999999989,
          "clipHeightFactor": 0.9999999999999993
        }
      },
      "cameraOffsets": {}
    }
  ],
  "elementsToHide": [],
  "selectedFrames": [
    "frame7041"
  ],
  "selectedLayers": [
    "layer1",
    "__sozi_auto__"
  ],
  "editableLayers": []
}